directory_downloader/__init__.py
directory_downloader/directory_downloader.py
directory_downloader-2.0.1.dist-info/LICENSE
directory_downloader-2.0.1.dist-info/METADATA
directory_downloader-2.0.1.dist-info/WHEEL
directory_downloader-2.0.1.dist-info/top_level.txt
directory_downloader-2.0.1.dist-info/RECORD
