Metadata-Version: 2.1
Name: directory-downloader
Version: 2.0.1
Summary: A python Package for downloading files from websites using the directory listing function
Home-page: https://github.com/SuperVegetoo/directory_downloader
Author: Super Vegetoo
Author-email: vegetoo255@gmail.com
License: UNKNOWN
Platform: UNKNOWN
Classifier: Programming Language :: Python :: 3
Classifier: License :: OSI Approved :: MIT License
Classifier: Operating System :: OS Independent
Requires-Python: >=3.6
License-File: LICENSE
Requires-Dist: bs4
Requires-Dist: aiohttp
